polishboiyt_utils/__init__.py
polishboiyt_utils/stdout.py
polishboiyt_utils/text.py
polishboiyt_utils-1.0.dist-info/LICENSE
polishboiyt_utils-1.0.dist-info/METADATA
polishboiyt_utils-1.0.dist-info/WHEEL
polishboiyt_utils-1.0.dist-info/top_level.txt
polishboiyt_utils-1.0.dist-info/RECORD
