Metadata-Version: 2.1
Name: polishboiyt-utils
Version: 1.0
Summary: Tools for people (like me) to make their lives easier.
Home-page: https://github.com/PolishBoiYT/polishboiyt-utils
Author: PolishBoiYT
Author-email: polishboiyt@gmail.com
Classifier: Programming Language :: Python :: 3
Classifier: License :: OSI Approved :: MIT License
Classifier: Operating System :: OS Independent
Requires-Python: >=3.9
License-File: LICENSE
